mldmtd/__init__.py
mldmtd/main.py
mldmtd-1.1.3.dist-info/licenses/LICENSE
mldmtd-1.1.3.dist-info/METADATA
mldmtd-1.1.3.dist-info/WHEEL
mldmtd-1.1.3.dist-info/top_level.txt
mldmtd-1.1.3.dist-info/RECORD
