Metadata-Version: 2.4
Name: mldmtd
Version: 1.1.3
Summary: Methodology to locate the minimum and maximum depth of the thermocline
Home-page: https://github.com/romeroqe/mld-mtd
Author: Emmanuel Romero
Author-email: romeroqe@gmail.com
License: CC-BY-4.0
Classifier: Programming Language :: Python :: 3
Classifier: License :: Other/Proprietary License
Classifier: Operating System :: OS Independent
License-File: LICENSE
Requires-Dist: numpy
Requires-Dist: pandas
Requires-Dist: gsw
Requires-Dist: netCDF4
Requires-Dist: scipy
Requires-Dist: scikit-learn
Dynamic: author
Dynamic: author-email
Dynamic: classifier
Dynamic: description
Dynamic: description-content-type
Dynamic: home-page
Dynamic: license
Dynamic: license-file
Dynamic: requires-dist
Dynamic: summary
